{"data":{"site":{"siteMetadata":{"title":"quickoverview","author":"Muhammad Awais Azmat"}},"markdownRemark":{"id":"4f716d07-a1bb-5945-ad86-a30c48bfa5b4","excerpt":"kjdakjdsal\nasjbcdskc\naskjcbdsackkjsac\nascjbsakcbjac\nasckajbvclancaskjbcxlkjsabvca\nascb,sabc,aasckjbsakcjbsalcnsa\nascbaksjbca\nascabs vclkjaca…","html":"<p>kjdakjdsal\nasjbcdskc\naskjcbdsackkjsac\nascjbsakcbjac\nasckajbvclanc</p>\n<p>askjbcxlkjsabvca\nascb,sabc,a</p>\n<p>asckjbsakcjbsalcnsa\nascbaksjbca\nascabs vclkjac</p>\n<p>a ckdsabvcsajbcakjcba</p>","frontmatter":{"title":"MindSet","date":"August 04, 2019"}}},"pageContext":{"isCreatedByStatefulCreatePages":false,"slug":"/mindset/","previous":{"fields":{"slug":"/the-five-love-languages/"},"frontmatter":{"title":"The 5 Love Languages"}},"next":null}}